discrete_dists-1.1.2.dist-info/METADATA
discrete_dists-1.1.2.dist-info/WHEEL
discrete_dists-1.1.2.dist-info/licenses/LICENSE
discrete_dists/rust/__init__.pyi
discrete_dists/proportional.py
discrete_dists/mixture.py
discrete_dists/py.typed
discrete_dists/utils/SumTree.py
discrete_dists/utils/__init__.py
discrete_dists/utils/npu.py
discrete_dists/__init__.py
discrete_dists/distribution.py
discrete_dists/uniform.py
discrete_dists/rust.cpython-312-x86_64-linux-gnu.so
discrete_dists-1.1.2.dist-info/RECORD
