Metadata-Version: 2.4
Name: discrete-dists
Version: 1.1.2
Classifier: Programming Language :: Rust
Classifier: Programming Language :: Python :: Implementation :: CPython
Classifier: Programming Language :: Python :: Implementation :: PyPy
Requires-Dist: numpy>=1.23,<3.0
Requires-Dist: pytest ; extra == 'dev'
Requires-Dist: maturin ; extra == 'dev'
Requires-Dist: pip ; extra == 'dev'
Requires-Dist: pytest-benchmark~=5.0 ; extra == 'dev'
Requires-Dist: ruff ; extra == 'dev'
Requires-Dist: pyright ; extra == 'dev'
Requires-Dist: commitizen ; extra == 'dev'
Requires-Dist: pre-commit ; extra == 'dev'
Provides-Extra: dev
License-File: LICENSE
Author-email: Andy Patterson <andnpatterson@gmail.com>
License: MIT
Requires-Python: >=3.10
Project-URL: Homepage, https://github.com/andnp/discrete-dists
Project-URL: Documentation, https://github.com/andnp/discrete-dists/blob/main/README.md
Project-URL: Repository, https://github.com/andnp/discrete-dists
Project-URL: Issues, https://github.com/andnp/discrete-dists/issues
Project-URL: Changelog, https://github.com/andnp/discrete-dists/blob/main/CHANGELOG.md
